pydae/.gitignore
pydae/__init__.py
pydae/b_pu.py
pydae/bpu.py
pydae/build.py
pydae/build_cffi.py
pydae/build_cffi_mp.py
pydae/build_test_cffi.c
pydae/build_v2.py
pydae/buildfast.py
pydae/checker.txt
pydae/ctrl.py
pydae/custom_functions.py
pydae/daesolver_ini.c
pydae/daesolver_ini.h
pydae/daesolver_ini.o
pydae/daesolver_run.c
pydae/daesolver_run.h
pydae/daesolver_run.o
pydae/grid_bpu.py
pydae/grid_data.json
pydae/grid_tools.py
pydae/grid_urisi.py
pydae/k12p6_pss.py
pydae/lines.py
pydae/matrices.npz
pydae/models.py
pydae/nummath.py
pydae/plot_tools.py
pydae/prueba.py
pydae/pydgrid.py
pydae/rdp.py
pydae/smib.c
pydae/solver_ini.c
pydae/solver_ini.o
pydae/solver_run.c
pydae/solver_run.o
pydae/solvers.py
pydae/ssa.py
pydae/temp.py
pydae/temp_ini_cffi.c
pydae/temp_run_cffi.c
pydae/temp_trap_cffi.c
pydae/tools.py
pydae/train_tools.py
pydae/transformers.py
pydae/xy_0.json
pydae/.ipynb_checkpoints/models-checkpoint.py
pydae/bmapu/__init__.py
pydae/bmapu/bmapu_builder.py
pydae/bmapu/avrs/__init__.py
pydae/bmapu/avrs/avr_antiw.py
pydae/bmapu/avrs/avrs.py
pydae/bmapu/avrs/avrs_study.ipynb
pydae/bmapu/avrs/energies-v14-i15_20221006.bib
pydae/bmapu/avrs/kundur.py
pydae/bmapu/avrs/kundur_tgr.py
pydae/bmapu/avrs/ntsst1.hjson
pydae/bmapu/avrs/ntsst1.py
pydae/bmapu/avrs/ntsst1_step.svg
pydae/bmapu/avrs/ntsst4.hjson
pydae/bmapu/avrs/ntsst4.py
pydae/bmapu/avrs/plot.svg
pydae/bmapu/avrs/pss_kundur_2.py
pydae/bmapu/avrs/sexs.hjson
pydae/bmapu/avrs/sexs.py
pydae/bmapu/avrs/sexs_dev.py
pydae/bmapu/avrs/sexs_step.svg
pydae/bmapu/avrs/smib_vsc_pq_inf.py
pydae/bmapu/avrs/smib_vsc_pq_inf_cffi.c
pydae/bmapu/avrs/temp.py
pydae/bmapu/avrs/temp_cffi.c
pydae/bmapu/avrs/temp_xy_0.json
pydae/bmapu/avrs/xy_0.json
pydae/bmapu/docs/trafo.md
pydae/bmapu/govs/__init__.py
pydae/bmapu/govs/agov1.py
pydae/bmapu/govs/govs.py
pydae/bmapu/govs/hygov.hjson
pydae/bmapu/govs/hygov.ipynb
pydae/bmapu/govs/hygov.py
pydae/bmapu/govs/hygov_step.svg
pydae/bmapu/govs/ieeeg1.hjson
pydae/bmapu/govs/ieeeg1.svg
pydae-0.56.5.dist-info/licenses/COPYING
pydae-0.56.5.dist-info/licenses/LICENSE
pydae-0.56.5.dist-info/WHEEL
pydae-0.56.5.dist-info/METADATA
pydae-0.56.5.dist-info/RECORD
