Metadata-Version: 2.4
Name: pydae
Version: 0.56.5
Summary: =====
Keywords: engineering
Author-email: Juan Manuel Mauricio <jmmauricio6@gmail.com>
Maintainer-email: Juan Manuel Mauricio <jmmauricio6@gmail.com>
Requires-Python: >=3.10
Classifier: License :: OSI Approved :: MIT License
Classifier: Development Status :: 4 - Beta
Classifier: Intended Audience :: Education
Classifier: Intended Audience :: Science/Research
Classifier: License :: OSI Approved :: MIT License
Classifier: Operating System :: OS Independent
Classifier: Programming Language :: Python
Classifier: Programming Language :: Python :: 3.10
Classifier: Programming Language :: Python :: 3.11
Classifier: Programming Language :: Python :: Implementation :: CPython
Classifier: Topic :: Scientific/Engineering
License-File: COPYING
License-File: LICENSE
Requires-Dist: numpy
Requires-Dist: scipy
Requires-Dist: sympy
Requires-Dist: numba
Requires-Dist: hjson
Requires-Dist: svgwrite
Requires-Dist: pandas
